config/__init__.py
exceptions/__init__.py
exceptions/router.py
manager/__init__.py
manager/plugin.py
manager/router.py
wexptend-0.1.2.dist-info/LICENSE
wexptend-0.1.2.dist-info/METADATA
wexptend-0.1.2.dist-info/WHEEL
wexptend-0.1.2.dist-info/top_level.txt
wexptend-0.1.2.dist-info/RECORD
