Metadata-Version: 2.2
Name: wexptend
Version: 0.1.2
Summary: A highly scalable websockets server framework.
Author-email: molanp <molanpp@outlook.com>
License: MIT
Project-URL: Bug Tracker, https://github.com/molanp/WExptend/issues
Project-URL: Homepage, https://github.com/molanp/WExptend
Classifier: Programming Language :: Python :: 3
Classifier: License :: OSI Approved :: MIT License
Classifier: Operating System :: OS Independent
Requires-Python: >=3.9
License-File: LICENSE
Requires-Dist: websockets
Requires-Dist: colorama
Requires-Dist: ujson
Requires-Dist: aiohttp
Requires-Dist: python-dotenv
Requires-Dist: watchdog
